LICENSE
MANIFEST.in
README.rst
setup.cfg
setup.py
solstice/__init__.py
solstice/tools/__init__.py
solstice/tools/snowgenerator/__init__.py
solstice/tools/snowgenerator/__version__.py
solstice/tools/snowgenerator/core/__init__.py
solstice/tools/snowgenerator/core/snowgenerator.py
solstice/tools/snowgenerator/resources/images/snowgenerator_logo.png
solstice/tools/snowgenerator/widgets/__init__.py
solstice/tools/snowgenerator/widgets/snowgenerator.py
solstice_tools_snowgenerator.egg-info/PKG-INFO
solstice_tools_snowgenerator.egg-info/SOURCES.txt
solstice_tools_snowgenerator.egg-info/dependency_links.txt
solstice_tools_snowgenerator.egg-info/not-zip-safe
solstice_tools_snowgenerator.egg-info/requires.txt
solstice_tools_snowgenerator.egg-info/top_level.txt
tests/__init__.py
tests/test_general.py