Metadata-Version: 2.1
Name: solstice-tools-snowgenerator
Version: 0.0.2
Summary: Tool to generate static snow meshes for Solstice
Home-page: https://github.com/Solstice-Short-Film/solstice-tools-snowgenerator
Author: Enrique Velasco
Author-email: enriquevelmai@hotmail.com
License: MIT
Platform: UNKNOWN
Provides-Extra: dev
Provides-Extra: test
